topsis_savree_102317097/__init__.py
topsis_savree_102317097/topsis.py
topsis_savree_102317097-0.0.1.dist-info/METADATA
topsis_savree_102317097-0.0.1.dist-info/WHEEL
topsis_savree_102317097-0.0.1.dist-info/entry_points.txt
topsis_savree_102317097-0.0.1.dist-info/top_level.txt
topsis_savree_102317097-0.0.1.dist-info/RECORD
