Metadata-Version: 2.4
Name: Topsis-Savree-102317097
Version: 0.0.1
Summary: TOPSIS implementation as a Python package
Author: Savree Dohar
Author-email: sdohar_be23@thapar.edu
Requires-Dist: pandas
Requires-Dist: numpy
Dynamic: author
Dynamic: author-email
Dynamic: description
Dynamic: description-content-type
Dynamic: requires-dist
Dynamic: summary
